Metadata-Version: 2.4
Name: blender-mcp-hunyuan
Version: 1.2.8
Summary: Blender integration through the Model Context Protocol
Author-email: neciszhang <903463144@qq.com>
License: MIT
Project-URL: Homepage, https://github.com/neciszhang/blender-mcp/tree/hunyuan
Project-URL: Bug Tracker, https://github.com/yourusername/blender-mcp/issues
Classifier: Programming Language :: Python :: 3
Classifier: License :: OSI Approved :: MIT License
Classifier: Operating System :: OS Independent
Requires-Python: >=3.12
License-File: LICENSE
Requires-Dist: mcp[cli]>=1.3.0
Dynamic: license-file
